streamlit_tensorboard/__init__.py
streamlit_tensorboard-0.0.2.dist-info/LICENSE
streamlit_tensorboard-0.0.2.dist-info/METADATA
streamlit_tensorboard-0.0.2.dist-info/WHEEL
streamlit_tensorboard-0.0.2.dist-info/top_level.txt
streamlit_tensorboard-0.0.2.dist-info/RECORD
