Metadata-Version: 2.1
Name: streamlit-tensorboard
Version: 0.0.2
Summary: Streamlit component for TensorBoard
Home-page: https://github.com/snehankekre/streamlit-tensorboard
Author: Snehan Kekre
Author-email: snehan@streamlit.io
License: UNKNOWN
Platform: UNKNOWN
Requires-Python: >=3.6
License-File: LICENSE
Requires-Dist: streamlit (>=0.63)
Requires-Dist: tensorboard (>=2.5.0)
